setup.py
variantannotation/MongoDB_querying.py
variantannotation/__init__.py
variantannotation/annotate_batch.py
variantannotation/annovar_processing.py
variantannotation/annovar_subprocess.py
variantannotation/create_output_files.py
variantannotation/csv_to_df.py
variantannotation/filtering_MongoDB_TEST.py
variantannotation/genotype_calling.py
variantannotation/main.py
variantannotation/mongo_DB_export.py
variantannotation/myvariant_parsing_utils.py
variantannotation/utilities.py
variantannotation.egg-info/PKG-INFO
variantannotation.egg-info/SOURCES.txt
variantannotation.egg-info/dependency_links.txt
variantannotation.egg-info/not-zip-safe
variantannotation.egg-info/requires.txt
variantannotation.egg-info/top_level.txt